ec2_provider/ec2_provider.py
ec2_provider/manifest.toml
ec2_provider/test_ec2_provider.py
opsbox_ec2_provider-0.1.5.dist-info/LICENCE.txt
opsbox_ec2_provider-0.1.5.dist-info/METADATA
opsbox_ec2_provider-0.1.5.dist-info/WHEEL
opsbox_ec2_provider-0.1.5.dist-info/entry_points.txt
opsbox_ec2_provider-0.1.5.dist-info/top_level.txt
opsbox_ec2_provider-0.1.5.dist-info/RECORD
