Metadata-Version: 2.2
Name: opsbox-ec2-provider
Version: 0.1.5
Summary: Opsbox provider for EC2 checks
License: Mozilla Public License Version 2.0
Requires-Python: ==3.11.*
License-File: LICENCE.txt
Requires-Dist: boto3>=1.35.87
Requires-Dist: loguru>=0.7.2
Requires-Dist: pluggy>=1.5.0
Requires-Dist: opsbox-general-handler>=0.1.2
